{
  "main": {
    "id": "f1b07aff1572df24",
    "type": "split",
    "children": [
      {
        "id": "3663de6a4cf88669",
        "type": "tabs",
        "children": [
          {
            "id": "1d5d14d3b80edaa4",
            "type": "leaf",
            "state": {
              "type": "empty",
              "state": {},
              "icon": "lucide-file",
              "title": "New tab"
            }
          }
        ]
      }
    ],
    "direction": "vertical"
  },
  "left": {
    "id": "a7022f4c5cade591",
    "type": "split",
    "children": [
      {
        "id": "5d3c1992ae1ed912",
        "type": "tabs",
        "children": [
          {
            "id": "bfa598aa5ef0b811",
            "type": "leaf",
            "state": {
              "type": "file-explorer",
              "state": {
                "sortOrder": "alphabetical",
                "autoReveal": false
              },
              "icon": "lucide-folder-closed",
              "title": "Files"
            }
          },
          {
            "id": "d24d6a9269dd82d3",
            "type": "leaf",
            "state": {
              "type": "search",
              "state": {
                "query": "",
                "matchingCase": false,
                "explainSearch": false,
                "collapseAll": false,
                "extraContext": false,
                "sortOrder": "alphabetical"
              },
              "icon": "lucide-search",
              "title": "Search"
            }
          },
          {
            "id": "27783c97db655aff",
            "type": "leaf",
            "state": {
              "type": "bookmarks",
              "state": {},
              "icon": "lucide-bookmark",
              "title": "Bookmarks"
            }
          }
        ]
      }
    ],
    "direction": "horizontal",
    "width": 300
  },
  "right": {
    "id": "4c4accca2fee4055",
    "type": "split",
    "children": [
      {
        "id": "615015ec4395c4f1",
        "type": "tabs",
        "children": [
          {
            "id": "f04fbef28d7f611a",
            "type": "leaf",
            "state": {
              "type": "backlink",
              "state": {
                "file": "World.canvas",
                "collapseAll": false,
                "extraContext": false,
                "sortOrder": "alphabetical",
                "showSearch": false,
                "searchQuery": "",
                "backlinkCollapsed": false,
                "unlinkedCollapsed": true
              },
              "icon": "links-coming-in",
              "title": "Backlinks for World"
            }
          },
          {
            "id": "eb1394a263aa311a",
            "type": "leaf",
            "state": {
              "type": "outgoing-link",
              "state": {
                "file": "World.canvas",
                "linksCollapsed": false,
                "unlinkedCollapsed": true
              },
              "icon": "links-going-out",
              "title": "Outgoing links from World"
            }
          },
          {
            "id": "ce08e6469c806736",
            "type": "leaf",
            "state": {
              "type": "tag",
              "state": {
                "sortOrder": "frequency",
                "useHierarchy": true,
                "showSearch": false,
                "searchQuery": ""
              },
              "icon": "lucide-tags",
              "title": "Tags"
            }
          },
          {
            "id": "f63a045e885cd144",
            "type": "leaf",
            "state": {
              "type": "outline",
              "state": {
                "file": "World.canvas",
                "followCursor": false,
                "showSearch": false,
                "searchQuery": ""
              },
              "icon": "lucide-list",
              "title": "Outline of World"
            }
          }
        ]
      }
    ],
    "direction": "horizontal",
    "width": 300,
    "collapsed": true
  },
  "left-ribbon": {
    "hiddenItems": {
      "switcher:Open quick switcher": false,
      "graph:Open graph view": false,
      "canvas:Create new canvas": false,
      "daily-notes:Open today's daily note": false,
      "templates:Insert template": false,
      "command-palette:Open command palette": false
    }
  },
  "active": "1d5d14d3b80edaa4",
  "lastOpenFiles": [
    "Untitled.md",
    "World.canvas",
    "Welcome.md"
  ]
}